ironhide/__init__.py
ironhide/py.typed
ironhide/settings.py
ironhide-0.1.11.dist-info/METADATA
ironhide-0.1.11.dist-info/WHEEL
ironhide-0.1.11.dist-info/licenses/LICENSE
ironhide-0.1.11.dist-info/RECORD
