Metadata-Version: 2.4
Name: ironhide
Version: 0.1.11
Summary: OOP llm agentic framework
Author-email: Lucas Martins Soares <lucasmsoares96@gmail.com>
License-File: LICENSE
Requires-Python: >=3.13
Requires-Dist: httpx>=0.28.1
Requires-Dist: pydantic-settings>=2.7.1
Requires-Dist: pydantic>=2.10.5
